LICENSE
README.md
pyproject.toml
src/xingshu/__init__.py
src/xingshu.egg-info/PKG-INFO
src/xingshu.egg-info/SOURCES.txt
src/xingshu.egg-info/dependency_links.txt
src/xingshu.egg-info/requires.txt
src/xingshu.egg-info/top_level.txt
src/xingshu/包_事件引擎/__init__.py
src/xingshu/包_事件引擎/模块_引擎.py
src/xingshu/包_交易核心/__init__.py
src/xingshu/包_交易核心/模块_主引擎.py
src/xingshu/包_交易核心/模块_事件类型.py
src/xingshu/包_交易核心/模块_基础数据库.py
src/xingshu/包_交易核心/模块_对象.py
src/xingshu/包_交易核心/模块_工具.py
src/xingshu/包_交易核心/模块_常数.py
src/xingshu/包_交易核心/模块_应用.py
src/xingshu/包_交易核心/模块_数据服务.py
src/xingshu/包_交易核心/模块_网关.py
src/xingshu/包_交易核心/模块_设置.py
src/xingshu/包_交易核心/模块_转换器.py
src/xingshu/包_交易核心/包_国际化/__init__.py