Metadata-Version: 2.4
Name: xingshu
Version: 1.0.2
Summary: 专为中文母语开发者打造的量化交易研发框架。
Author-email: bhzy <2024305928@qq.com>
License-Expression: MIT
Project-URL: Homepage, https://github.com/bhzyxyqy/xingshu
Project-URL: Issues, https://github.com/bhzyxyqy/xingshu/issues
Classifier: Programming Language :: Python :: 3
Classifier: Operating System :: OS Independent
Requires-Python: >=3.8
License-File: LICENSE
Requires-Dist: numpy>=2.2.3
Requires-Dist: ta-lib>=0.6.0
Requires-Dist: tzlocal>=5.3
Requires-Dist: xingshu_ctp>=0.0.1
Requires-Dist: xingshu-sqlite>=0.0.1
Requires-Dist: xingshu-cta-jymokuai>=1.0.1
Dynamic: license-file
